<?xml version="1.0" encoding="UTF-8" standalone="yes"?>
<p:sld xmlns:a="http://schemas.openxmlformats.org/drawingml/2006/main" xmlns:r="http://schemas.openxmlformats.org/officeDocument/2006/relationships" xmlns:p="http://schemas.openxmlformats.org/presentationml/2006/main"><p:cSld><p:bg><p:bgPr><a:solidFill><a:schemeClr val="bg1"/></a:solidFill><a:effectLst/></p:bgPr></p:bg><p:spTree><p:nvGrpSpPr><p:cNvPr id="1" name=""/><p:cNvGrpSpPr/><p:nvPr/></p:nvGrpSpPr><p:grpSpPr><a:xfrm><a:off x="0" y="0"/><a:ext cx="0" cy="0"/><a:chOff x="0" y="0"/><a:chExt cx="0" cy="0"/></a:xfrm></p:grpSpPr><p:sp><p:nvSpPr><p:cNvPr id="2" name="Заголовок 1"/><p:cNvSpPr><a:spLocks noGrp="1"/></p:cNvSpPr><p:nvPr><p:ph type="title"/></p:nvPr></p:nvSpPr><p:spPr><a:xfrm><a:off x="500743" y="0"/><a:ext cx="11691257" cy="1485900"/></a:xfrm></p:spPr><p:txBody><a:bodyPr><a:noAutofit/></a:bodyPr><a:lstStyle/><a:p><a:pPr lvl="0" algn="ctr"/><a:r><a:rPr lang="en-US" sz="4000" b="1" dirty="0"><a:latin typeface="Times New Roman" charset="0"/><a:ea typeface="Times New Roman" charset="0"/><a:cs typeface="Times New Roman" charset="0"/></a:rPr><a:t>5.Взаимоотношение </a:t></a:r><a:r><a:rPr lang="en-US" sz="4000" b="1" dirty="0" err="1"><a:latin typeface="Times New Roman" charset="0"/><a:ea typeface="Times New Roman" charset="0"/><a:cs typeface="Times New Roman" charset="0"/></a:rPr><a:t>между</a:t></a:r><a:r><a:rPr lang="en-US" sz="4000" b="1" dirty="0"><a:latin typeface="Times New Roman" charset="0"/><a:ea typeface="Times New Roman" charset="0"/><a:cs typeface="Times New Roman" charset="0"/></a:rPr><a:t> </a:t></a:r><a:br><a:rPr lang="en-US" sz="4000" b="1" dirty="0"><a:latin typeface="Times New Roman" charset="0"/><a:ea typeface="Times New Roman" charset="0"/><a:cs typeface="Times New Roman" charset="0"/></a:rPr></a:br><a:r><a:rPr lang="en-US" sz="4000" b="1" dirty="0" err="1"><a:latin typeface="Times New Roman" charset="0"/><a:ea typeface="Times New Roman" charset="0"/><a:cs typeface="Times New Roman" charset="0"/></a:rPr><a:t>христианским</a:t></a:r><a:r><a:rPr lang="en-US" sz="4000" b="1" dirty="0"><a:latin typeface="Times New Roman" charset="0"/><a:ea typeface="Times New Roman" charset="0"/><a:cs typeface="Times New Roman" charset="0"/></a:rPr><a:t> </a:t></a:r><a:r><a:rPr lang="en-US" sz="4000" b="1" dirty="0" err="1"><a:latin typeface="Times New Roman" charset="0"/><a:ea typeface="Times New Roman" charset="0"/><a:cs typeface="Times New Roman" charset="0"/></a:rPr><a:t>мировозрением</a:t></a:r><a:r><a:rPr lang="en-US" sz="4000" b="1" dirty="0"><a:latin typeface="Times New Roman" charset="0"/><a:ea typeface="Times New Roman" charset="0"/><a:cs typeface="Times New Roman" charset="0"/></a:rPr><a:t> </a:t></a:r><a:r><a:rPr lang="en-US" sz="4000" b="1" dirty="0" err="1"><a:latin typeface="Times New Roman" charset="0"/><a:ea typeface="Times New Roman" charset="0"/><a:cs typeface="Times New Roman" charset="0"/></a:rPr><a:t>и</a:t></a:r><a:r><a:rPr lang="en-US" sz="4000" b="1" dirty="0"><a:latin typeface="Times New Roman" charset="0"/><a:ea typeface="Times New Roman" charset="0"/><a:cs typeface="Times New Roman" charset="0"/></a:rPr><a:t> </a:t></a:r><a:r><a:rPr lang="ru-RU" sz="4000" b="1" dirty="0" err="1"><a:latin typeface="Times New Roman" charset="0"/><a:ea typeface="Times New Roman" charset="0"/><a:cs typeface="Times New Roman" charset="0"/></a:rPr><a:t>б</a:t></a:r><a:r><a:rPr lang="en-US" sz="4000" b="1" dirty="0" err="1"><a:latin typeface="Times New Roman" charset="0"/><a:ea typeface="Times New Roman" charset="0"/><a:cs typeface="Times New Roman" charset="0"/></a:rPr><a:t>огословием</a:t></a:r><a:r><a:rPr lang="en-US" sz="4000" b="1" dirty="0"><a:latin typeface="Times New Roman" charset="0"/><a:ea typeface="Times New Roman" charset="0"/><a:cs typeface="Times New Roman" charset="0"/></a:rPr><a:t> </a:t></a:r><a:br><a:rPr lang="ru-RU" sz="4000" b="1" dirty="0"><a:latin typeface="Times New Roman" charset="0"/><a:ea typeface="Times New Roman" charset="0"/><a:cs typeface="Times New Roman" charset="0"/></a:rPr></a:br><a:endParaRPr lang="ru-RU" sz="4000" b="1" dirty="0"><a:latin typeface="Times New Roman" charset="0"/><a:ea typeface="Times New Roman" charset="0"/><a:cs typeface="Times New Roman" charset="0"/></a:endParaRPr></a:p></p:txBody></p:sp><p:sp><p:nvSpPr><p:cNvPr id="3" name="Объект 2"/><p:cNvSpPr><a:spLocks noGrp="1"/></p:cNvSpPr><p:nvPr><p:ph idx="1"/></p:nvPr></p:nvSpPr><p:spPr><a:xfrm><a:off x="1545771" y="1485900"/><a:ext cx="9601200" cy="3581400"/></a:xfrm></p:spPr><p:txBody><a:bodyPr><a:noAutofit/></a:bodyPr><a:lstStyle/><a:p><a:pPr marL="514350" lvl="1" indent="-514350"><a:buFont typeface="+mj-lt"/><a:buAutoNum type="alphaLcPeriod"/></a:pPr><a:r><a:rPr lang="ru-RU" sz="3000" b="1" i="0" dirty="0"><a:latin typeface="Times New Roman" charset="0"/><a:ea typeface="Times New Roman" charset="0"/><a:cs typeface="Times New Roman" charset="0"/></a:rPr><a:t>Богословие рассматривает духовное основание христианского </a:t></a:r><a:r><a:rPr lang="ru-RU" sz="3000" b="1" i="0" dirty="0" err="1"><a:latin typeface="Times New Roman" charset="0"/><a:ea typeface="Times New Roman" charset="0"/><a:cs typeface="Times New Roman" charset="0"/></a:rPr><a:t>мировозрения</a:t></a:r><a:r><a:rPr lang="ru-RU" sz="3000" b="1" i="0" dirty="0"><a:latin typeface="Times New Roman" charset="0"/><a:ea typeface="Times New Roman" charset="0"/><a:cs typeface="Times New Roman" charset="0"/></a:rPr><a:t>.</a:t></a:r></a:p><a:p><a:pPr marL="514350" lvl="1" indent="-514350"><a:buFont typeface="+mj-lt"/><a:buAutoNum type="alphaLcPeriod"/></a:pPr><a:r><a:rPr lang="en-US" sz="3000" b="1" i="0" dirty="0" err="1"><a:latin typeface="Times New Roman" charset="0"/><a:ea typeface="Times New Roman" charset="0"/><a:cs typeface="Times New Roman" charset="0"/></a:rPr><a:t>Богословие</a:t></a:r><a:r><a:rPr lang="en-US" sz="3000" b="1" i="0" dirty="0"><a:latin typeface="Times New Roman" charset="0"/><a:ea typeface="Times New Roman" charset="0"/><a:cs typeface="Times New Roman" charset="0"/></a:rPr><a:t> </a:t></a:r><a:r><a:rPr lang="en-US" sz="3000" b="1" i="0" dirty="0" err="1"><a:latin typeface="Times New Roman" charset="0"/><a:ea typeface="Times New Roman" charset="0"/><a:cs typeface="Times New Roman" charset="0"/></a:rPr><a:t>исследует</a:t></a:r><a:r><a:rPr lang="en-US" sz="3000" b="1" i="0" dirty="0"><a:latin typeface="Times New Roman" charset="0"/><a:ea typeface="Times New Roman" charset="0"/><a:cs typeface="Times New Roman" charset="0"/></a:rPr><a:t> </a:t></a:r><a:r><a:rPr lang="en-US" sz="3000" b="1" i="0" dirty="0" err="1"><a:latin typeface="Times New Roman" charset="0"/><a:ea typeface="Times New Roman" charset="0"/><a:cs typeface="Times New Roman" charset="0"/></a:rPr><a:t>интеллектуальн</a:t></a:r><a:r><a:rPr lang="ru-RU" sz="3000" b="1" i="0" dirty="0" err="1"><a:latin typeface="Times New Roman" charset="0"/><a:ea typeface="Times New Roman" charset="0"/><a:cs typeface="Times New Roman" charset="0"/></a:rPr><a:t>ое</a:t></a:r><a:r><a:rPr lang="ru-RU" sz="3000" b="1" i="0" dirty="0"><a:latin typeface="Times New Roman" charset="0"/><a:ea typeface="Times New Roman" charset="0"/><a:cs typeface="Times New Roman" charset="0"/></a:rPr><a:t> основание х</a:t></a:r><a:r><a:rPr lang="en-US" sz="3000" b="1" i="0" dirty="0" err="1"><a:latin typeface="Times New Roman" charset="0"/><a:ea typeface="Times New Roman" charset="0"/><a:cs typeface="Times New Roman" charset="0"/></a:rPr><a:t>ристианского</a:t></a:r><a:r><a:rPr lang="en-US" sz="3000" b="1" i="0" dirty="0"><a:latin typeface="Times New Roman" charset="0"/><a:ea typeface="Times New Roman" charset="0"/><a:cs typeface="Times New Roman" charset="0"/></a:rPr><a:t> </a:t></a:r><a:r><a:rPr lang="ru-RU" sz="3000" b="1" i="0" dirty="0" err="1"><a:latin typeface="Times New Roman" charset="0"/><a:ea typeface="Times New Roman" charset="0"/><a:cs typeface="Times New Roman" charset="0"/></a:rPr><a:t>м</a:t></a:r><a:r><a:rPr lang="en-US" sz="3000" b="1" i="0" dirty="0" err="1"><a:latin typeface="Times New Roman" charset="0"/><a:ea typeface="Times New Roman" charset="0"/><a:cs typeface="Times New Roman" charset="0"/></a:rPr><a:t>ировозрения</a:t></a:r><a:r><a:rPr lang="en-US" sz="3000" b="1" i="0" dirty="0"><a:latin typeface="Times New Roman" charset="0"/><a:ea typeface="Times New Roman" charset="0"/><a:cs typeface="Times New Roman" charset="0"/></a:rPr><a:t>.   </a:t></a:r><a:endParaRPr lang="ru-RU" sz="3000" b="1" i="0" dirty="0"><a:latin typeface="Times New Roman" charset="0"/><a:ea typeface="Times New Roman" charset="0"/><a:cs typeface="Times New Roman" charset="0"/></a:endParaRPr></a:p><a:p><a:pPr marL="514350" lvl="1" indent="-514350"><a:buFont typeface="+mj-lt"/><a:buAutoNum type="alphaLcPeriod"/></a:pPr><a:r><a:rPr lang="en-US" sz="3000" b="1" i="0" dirty="0" err="1"><a:latin typeface="Times New Roman" charset="0"/><a:ea typeface="Times New Roman" charset="0"/><a:cs typeface="Times New Roman" charset="0"/></a:rPr><a:t>Богословие</a:t></a:r><a:r><a:rPr lang="en-US" sz="3000" b="1" i="0" dirty="0"><a:latin typeface="Times New Roman" charset="0"/><a:ea typeface="Times New Roman" charset="0"/><a:cs typeface="Times New Roman" charset="0"/></a:rPr><a:t> </a:t></a:r><a:r><a:rPr lang="en-US" sz="3000" b="1" i="0" dirty="0" err="1"><a:latin typeface="Times New Roman" charset="0"/><a:ea typeface="Times New Roman" charset="0"/><a:cs typeface="Times New Roman" charset="0"/></a:rPr><a:t>закладывает</a:t></a:r><a:r><a:rPr lang="en-US" sz="3000" b="1" i="0" dirty="0"><a:latin typeface="Times New Roman" charset="0"/><a:ea typeface="Times New Roman" charset="0"/><a:cs typeface="Times New Roman" charset="0"/></a:rPr><a:t> </a:t></a:r><a:r><a:rPr lang="en-US" sz="3000" b="1" i="0" dirty="0" err="1"><a:latin typeface="Times New Roman" charset="0"/><a:ea typeface="Times New Roman" charset="0"/><a:cs typeface="Times New Roman" charset="0"/></a:rPr><a:t>основу</a:t></a:r><a:r><a:rPr lang="en-US" sz="3000" b="1" i="0" dirty="0"><a:latin typeface="Times New Roman" charset="0"/><a:ea typeface="Times New Roman" charset="0"/><a:cs typeface="Times New Roman" charset="0"/></a:rPr><a:t> </a:t></a:r><a:r><a:rPr lang="en-US" sz="3000" b="1" i="0" dirty="0" err="1"><a:latin typeface="Times New Roman" charset="0"/><a:ea typeface="Times New Roman" charset="0"/><a:cs typeface="Times New Roman" charset="0"/></a:rPr><a:t>для</a:t></a:r><a:r><a:rPr lang="en-US" sz="3000" b="1" i="0" dirty="0"><a:latin typeface="Times New Roman" charset="0"/><a:ea typeface="Times New Roman" charset="0"/><a:cs typeface="Times New Roman" charset="0"/></a:rPr><a:t> </a:t></a:r><a:r><a:rPr lang="en-US" sz="3000" b="1" i="0" dirty="0" err="1"><a:latin typeface="Times New Roman" charset="0"/><a:ea typeface="Times New Roman" charset="0"/><a:cs typeface="Times New Roman" charset="0"/></a:rPr><a:t>проявления</a:t></a:r><a:r><a:rPr lang="en-US" sz="3000" b="1" i="0" dirty="0"><a:latin typeface="Times New Roman" charset="0"/><a:ea typeface="Times New Roman" charset="0"/><a:cs typeface="Times New Roman" charset="0"/></a:rPr><a:t> </a:t></a:r><a:r><a:rPr lang="ru-RU" sz="3000" b="1" i="0" dirty="0" err="1"><a:latin typeface="Times New Roman" charset="0"/><a:ea typeface="Times New Roman" charset="0"/><a:cs typeface="Times New Roman" charset="0"/></a:rPr><a:t>х</a:t></a:r><a:r><a:rPr lang="en-US" sz="3000" b="1" i="0" dirty="0" err="1"><a:latin typeface="Times New Roman" charset="0"/><a:ea typeface="Times New Roman" charset="0"/><a:cs typeface="Times New Roman" charset="0"/></a:rPr><a:t>ристианского</a:t></a:r><a:r><a:rPr lang="en-US" sz="3000" b="1" i="0" dirty="0"><a:latin typeface="Times New Roman" charset="0"/><a:ea typeface="Times New Roman" charset="0"/><a:cs typeface="Times New Roman" charset="0"/></a:rPr><a:t> </a:t></a:r><a:r><a:rPr lang="ru-RU" sz="3000" b="1" i="0" dirty="0" err="1"><a:latin typeface="Times New Roman" charset="0"/><a:ea typeface="Times New Roman" charset="0"/><a:cs typeface="Times New Roman" charset="0"/></a:rPr><a:t>м</a:t></a:r><a:r><a:rPr lang="en-US" sz="3000" b="1" i="0" dirty="0" err="1"><a:latin typeface="Times New Roman" charset="0"/><a:ea typeface="Times New Roman" charset="0"/><a:cs typeface="Times New Roman" charset="0"/></a:rPr><a:t>ировозрения</a:t></a:r><a:r><a:rPr lang="en-US" sz="3000" b="1" i="0" dirty="0"><a:latin typeface="Times New Roman" charset="0"/><a:ea typeface="Times New Roman" charset="0"/><a:cs typeface="Times New Roman" charset="0"/></a:rPr><a:t>. </a:t></a:r><a:endParaRPr lang="ru-RU" sz="3000" b="1" i="0" dirty="0"><a:latin typeface="Times New Roman" charset="0"/><a:ea typeface="Times New Roman" charset="0"/><a:cs typeface="Times New Roman" charset="0"/></a:endParaRPr></a:p><a:p><a:pPr marL="514350" lvl="1" indent="-514350"><a:buFont typeface="+mj-lt"/><a:buAutoNum type="alphaLcPeriod"/></a:pPr><a:r><a:rPr lang="en-US" sz="3000" b="1" i="0" dirty="0" err="1"><a:latin typeface="Times New Roman" charset="0"/><a:ea typeface="Times New Roman" charset="0"/><a:cs typeface="Times New Roman" charset="0"/></a:rPr><a:t>Богословие</a:t></a:r><a:r><a:rPr lang="en-US" sz="3000" b="1" i="0" dirty="0"><a:latin typeface="Times New Roman" charset="0"/><a:ea typeface="Times New Roman" charset="0"/><a:cs typeface="Times New Roman" charset="0"/></a:rPr><a:t> </a:t></a:r><a:r><a:rPr lang="en-US" sz="3000" b="1" i="0" dirty="0" err="1"><a:latin typeface="Times New Roman" charset="0"/><a:ea typeface="Times New Roman" charset="0"/><a:cs typeface="Times New Roman" charset="0"/></a:rPr><a:t>сранивает</a:t></a:r><a:r><a:rPr lang="en-US" sz="3000" b="1" i="0" dirty="0"><a:latin typeface="Times New Roman" charset="0"/><a:ea typeface="Times New Roman" charset="0"/><a:cs typeface="Times New Roman" charset="0"/></a:rPr><a:t> </a:t></a:r><a:r><a:rPr lang="en-US" sz="3000" b="1" i="0" dirty="0" err="1"><a:latin typeface="Times New Roman" charset="0"/><a:ea typeface="Times New Roman" charset="0"/><a:cs typeface="Times New Roman" charset="0"/></a:rPr><a:t>библейское</a:t></a:r><a:r><a:rPr lang="en-US" sz="3000" b="1" i="0" dirty="0"><a:latin typeface="Times New Roman" charset="0"/><a:ea typeface="Times New Roman" charset="0"/><a:cs typeface="Times New Roman" charset="0"/></a:rPr><a:t> </a:t></a:r><a:r><a:rPr lang="en-US" sz="3000" b="1" i="0" dirty="0" err="1"><a:latin typeface="Times New Roman" charset="0"/><a:ea typeface="Times New Roman" charset="0"/><a:cs typeface="Times New Roman" charset="0"/></a:rPr><a:t>учение</a:t></a:r><a:r><a:rPr lang="en-US" sz="3000" b="1" i="0" dirty="0"><a:latin typeface="Times New Roman" charset="0"/><a:ea typeface="Times New Roman" charset="0"/><a:cs typeface="Times New Roman" charset="0"/></a:rPr><a:t> </a:t></a:r><a:r><a:rPr lang="en-US" sz="3000" b="1" i="0" dirty="0" err="1"><a:latin typeface="Times New Roman" charset="0"/><a:ea typeface="Times New Roman" charset="0"/><a:cs typeface="Times New Roman" charset="0"/></a:rPr><a:t>и</a:t></a:r><a:r><a:rPr lang="en-US" sz="3000" b="1" i="0" dirty="0"><a:latin typeface="Times New Roman" charset="0"/><a:ea typeface="Times New Roman" charset="0"/><a:cs typeface="Times New Roman" charset="0"/></a:rPr><a:t> </a:t></a:r><a:r><a:rPr lang="en-US" sz="3000" b="1" i="0" dirty="0" err="1"><a:latin typeface="Times New Roman" charset="0"/><a:ea typeface="Times New Roman" charset="0"/><a:cs typeface="Times New Roman" charset="0"/></a:rPr><a:t>нашу</a:t></a:r><a:r><a:rPr lang="en-US" sz="3000" b="1" i="0" dirty="0"><a:latin typeface="Times New Roman" charset="0"/><a:ea typeface="Times New Roman" charset="0"/><a:cs typeface="Times New Roman" charset="0"/></a:rPr><a:t> </a:t></a:r><a:r><a:rPr lang="en-US" sz="3000" b="1" i="0" dirty="0" err="1"><a:latin typeface="Times New Roman" charset="0"/><a:ea typeface="Times New Roman" charset="0"/><a:cs typeface="Times New Roman" charset="0"/></a:rPr><a:t>христианскую</a:t></a:r><a:r><a:rPr lang="en-US" sz="3000" b="1" i="0" dirty="0"><a:latin typeface="Times New Roman" charset="0"/><a:ea typeface="Times New Roman" charset="0"/><a:cs typeface="Times New Roman" charset="0"/></a:rPr><a:t> </a:t></a:r><a:r><a:rPr lang="en-US" sz="3000" b="1" i="0" dirty="0" err="1"><a:latin typeface="Times New Roman" charset="0"/><a:ea typeface="Times New Roman" charset="0"/><a:cs typeface="Times New Roman" charset="0"/></a:rPr><a:t>практику</a:t></a:r><a:r><a:rPr lang="en-US" sz="3000" b="1" i="0" dirty="0"><a:latin typeface="Times New Roman" charset="0"/><a:ea typeface="Times New Roman" charset="0"/><a:cs typeface="Times New Roman" charset="0"/></a:rPr><a:t>.</a:t></a:r><a:endParaRPr lang="ru-RU" sz="3000" b="1" i="0" dirty="0"><a:latin typeface="Times New Roman" charset="0"/><a:ea typeface="Times New Roman" charset="0"/><a:cs typeface="Times New Roman" charset="0"/></a:endParaRPr></a:p><a:p><a:pPr marL="514350" lvl="1" indent="-514350"><a:buFont typeface="+mj-lt"/><a:buAutoNum type="alphaLcPeriod"/></a:pPr><a:r><a:rPr lang="en-US" sz="3000" b="1" i="0" dirty="0" err="1"><a:latin typeface="Times New Roman" charset="0"/><a:ea typeface="Times New Roman" charset="0"/><a:cs typeface="Times New Roman" charset="0"/></a:rPr><a:t>Богословие</a:t></a:r><a:r><a:rPr lang="en-US" sz="3000" b="1" i="0" dirty="0"><a:latin typeface="Times New Roman" charset="0"/><a:ea typeface="Times New Roman" charset="0"/><a:cs typeface="Times New Roman" charset="0"/></a:rPr><a:t> </a:t></a:r><a:r><a:rPr lang="en-US" sz="3000" b="1" i="0" dirty="0" err="1"><a:latin typeface="Times New Roman" charset="0"/><a:ea typeface="Times New Roman" charset="0"/><a:cs typeface="Times New Roman" charset="0"/></a:rPr><a:t>критикует</a:t></a:r><a:r><a:rPr lang="en-US" sz="3000" b="1" i="0" dirty="0"><a:latin typeface="Times New Roman" charset="0"/><a:ea typeface="Times New Roman" charset="0"/><a:cs typeface="Times New Roman" charset="0"/></a:rPr><a:t> </a:t></a:r><a:r><a:rPr lang="en-US" sz="3000" b="1" i="0" dirty="0" err="1"><a:latin typeface="Times New Roman" charset="0"/><a:ea typeface="Times New Roman" charset="0"/><a:cs typeface="Times New Roman" charset="0"/></a:rPr><a:t>наши</a:t></a:r><a:r><a:rPr lang="en-US" sz="3000" b="1" i="0" dirty="0"><a:latin typeface="Times New Roman" charset="0"/><a:ea typeface="Times New Roman" charset="0"/><a:cs typeface="Times New Roman" charset="0"/></a:rPr><a:t> </a:t></a:r><a:r><a:rPr lang="en-US" sz="3000" b="1" i="0" dirty="0" err="1"><a:latin typeface="Times New Roman" charset="0"/><a:ea typeface="Times New Roman" charset="0"/><a:cs typeface="Times New Roman" charset="0"/></a:rPr><a:t>культурные</a:t></a:r><a:r><a:rPr lang="en-US" sz="3000" b="1" i="0" dirty="0"><a:latin typeface="Times New Roman" charset="0"/><a:ea typeface="Times New Roman" charset="0"/><a:cs typeface="Times New Roman" charset="0"/></a:rPr><a:t> </a:t></a:r><a:r><a:rPr lang="ru-RU" sz="3000" b="1" i="0" dirty="0"><a:latin typeface="Times New Roman" charset="0"/><a:ea typeface="Times New Roman" charset="0"/><a:cs typeface="Times New Roman" charset="0"/></a:rPr><a:t>представления</a:t></a:r></a:p><a:p><a:pPr marL="514350" indent="-514350"><a:buFont typeface="+mj-lt"/><a:buAutoNum type="alphaLcPeriod"/></a:pPr><a:endParaRPr lang="ru-RU" sz="3000" b="1" dirty="0"><a:latin typeface="Times New Roman" charset="0"/><a:ea typeface="Times New Roman" charset="0"/><a:cs typeface="Times New Roman" charset="0"/></a:endParaRPr></a:p></p:txBody></p:sp></p:spTree><p:extLst><p:ext uri="{BB962C8B-B14F-4D97-AF65-F5344CB8AC3E}"><p14:creationId xmlns:p14="http://schemas.microsoft.com/office/powerpoint/2010/main" val="1973884"/></p:ext></p:extLst></p:cSld><p:clrMapOvr><a:masterClrMapping/></p:clrMapOvr></p:sld>